[{"__type__":"cc.SpriteFrame","content":{"name":"popKuang_S","texture":"18gxpTh89LMbx6gPDjn0oX","rect":[0,0,730,1018],"offset":[0,0],"originalSize":[730,1018],"capInsets":[362,490,362,490]}},{"__type__":"cc.SpriteFrame","content":{"name":"btnAd","texture":"7fSCPFdEFGh5HKiBTzna5A","rect":[2,1056,350,101],"offset":[0,0],"originalSize":[350,101],"capInsets":[158,0,158,0]}},{"__type__":"cc.SpriteFrame","content":{"name":"default_sprite_splash","texture":"02delMVqdBD70a/HSD99FK","rect":[0,0,2,2],"offset":[0,0],"originalSize":[2,2],"capInsets":[0,0,0,0]}},{"__type__":"cc.SpriteFrame","content":{"name":"btnClose","texture":"7fSCPFdEFGh5HKiBTzna5A","rect":[78,1785,68,68],"offset":[0,0],"originalSize":[68,68],"capInsets":[0,0,0,0]}},[{"__type__":"cc.Prefab","_name":"BankLayer","data":{"__id__":1}},{"__type__":"cc.Node","_name":"BankLayer","_children":[{"__id__":2},{"__id__":3}],"_components":[{"__type__":"cc.Widget","node":{"__id__":1},"_alignFlags":45},{"__type__":"aa85aLD58JApo4DIvBOFqAe","node":{"__id__":1},"lblStar":{"__id__":8},"lblMoney":{"__id__":13}}],"_prefab":{"__type__":"cc.PrefabInfo","root":{"__id__":1},"asset":{"__uuid__":"b5ayNS52NPdoOAV82HHCM9"},"fileId":"7bbPkoQVtKyKb1V5RRiUOx"},"_contentSize":{"__type__":"cc.Size","width":1080,"height":1920},"_trs":{"__type__":"TypedArray","ctor":"Float64Array","array":[540,960,0,0,0,0,1,1,1,1]}},{"__type__":"cc.Node","_name":"New Sprite(Splash)","_parent":{"__id__":1},"_components":[{"__type__":"cc.Sprite","node":{"__id__":2},"_materials":[{"__uuid__":"ecpdLyjvZBwrvm+cedCcQy"}],"_spriteFrame":{"__uuid__":"a2MjXRFdtLlYQ5ouAFv/+R"},"_sizeMode":0},{"__type__":"cc.Widget","node":{"__id__":2},"_alignFlags":45,"_originalWidth":100,"_originalHeight":100}],"_prefab":{"__type__":"cc.PrefabInfo","root":{"__id__":1},"asset":{"__uuid__":"b5ayNS52NPdoOAV82HHCM9"},"fileId":"b6f7Y3yr9Ho5U4jmvKEzCh"},"_opacity":120,"_color":{"__type__":"cc.Color","r":46,"g":39,"b":39},"_contentSize":{"__type__":"cc.Size","width":1080,"height":1920},"_trs":{"__type__":"TypedArray","ctor":"Float64Array","array":[0,0,0,0,0,0,1,1,1,1]}},{"__type__":"cc.Node","_name":"popupFrame","_parent":{"__id__":1},"_children":[{"__id__":4},{"__id__":5},{"__id__":6},{"__id__":9},{"__id__":11},{"__id__":12},{"__id__":14}],"_components":[{"__type__":"cc.Sprite","node":{"__id__":3},"_materials":[{"__uuid__":"ecpdLyjvZBwrvm+cedCcQy"}],"_spriteFrame":{"__uuid__":"0eRtVld5lMv6UCPVe7Vj46"},"_type":1,"_sizeMode":0}],"_prefab":{"__type__":"cc.PrefabInfo","root":{"__id__":1},"asset":{"__uuid__":"b5ayNS52NPdoOAV82HHCM9"},"fileId":"8eid8PvWdJ5ZFUVMczSd//"},"_contentSize":{"__type__":"cc.Size","width":730,"height":1018},"_trs":{"__type__":"TypedArray","ctor":"Float64Array","array":[0,0,0,0,0,0,1,1,1,1]}},{"__type__":"cc.Node","_name":"btnClose","_parent":{"__id__":3},"_components":[{"__type__":"cc.Sprite","node":{"__id__":4},"_materials":[{"__uuid__":"ecpdLyjvZBwrvm+cedCcQy"}],"_spriteFrame":{"__uuid__":"aehRPGHDRHv4zgMuui1RMg"}},{"__type__":"cc.Widget","node":{"__id__":4},"_alignFlags":33},{"__type__":"cc.Button","node":{"__id__":4},"clickEvents":[{"__type__":"cc.ClickEvent","target":{"__id__":1},"_componentId":"aa85aLD58JApo4DIvBOFqAe","handler":"onBtnClickToClose"}],"_N$transition":3,"transition":3,"_N$normalColor":{"__type__":"cc.Color","r":214,"g":214,"b":214}},{"__type__":"045a2SGe7RBVLBIutN8jPMM","node":{"__id__":4}},{"__type__":"03d50qD7WhNnpmfgnS9N+eO","node":{"__id__":4}}],"_prefab":{"__type__":"cc.PrefabInfo","root":{"__id__":1},"asset":{"__uuid__":"b5ayNS52NPdoOAV82HHCM9"},"fileId":"8b0in7POFMCaWyQBsrLg5n"},"_opacity":0,"_contentSize":{"__type__":"cc.Size","width":68,"height":68},"_trs":{"__type__":"TypedArray","ctor":"Float64Array","array":[331,475,0,0,0,0,1,1,1,1]}},{"__type__":"cc.Node","_name":"bankIcon","_parent":{"__id__":3},"_components":[{"__type__":"sp.Skeleton","node":{"__id__":5},"_materials":[{"__uuid__":"7a/QZLET9IDreTiBfRn2PD"}],"defaultAnimation":"animation","_preCacheMode":0,"_animationName":"animation","_N$skeletonData":{"__uuid__":"a1xLsH1IhK8ryajiFZp7fl"}}],"_prefab":{"__type__":"cc.PrefabInfo","root":{"__id__":1},"asset":{"__uuid__":"b5ayNS52NPdoOAV82HHCM9"},"fileId":"e1uV/vaZBNabVCVpTOhvxp"},"_contentSize":{"__type__":"cc.Size","width":200,"height":200},"_trs":{"__type__":"TypedArray","ctor":"Float64Array","array":[0,144.77000000000004,0,0,0,0,1,2,2,1]}},{"__type__":"cc.Node","_name":"btnGet","_parent":{"__id__":3},"_children":[{"__id__":7}],"_components":[{"__type__":"cc.Sprite","node":{"__id__":6},"_materials":[{"__uuid__":"ecpdLyjvZBwrvm+cedCcQy"}],"_spriteFrame":{"__uuid__":"bddtvDcTlDVannbcUdYPRZ"},"_type":1,"_sizeMode":0},{"__type__":"cc.Widget","node":{"__id__":6},"_alignFlags":1,"_top":815.884},{"__type__":"cc.Button","node":{"__id__":6},"clickEvents":[{"__type__":"cc.ClickEvent","target":{"__id__":1},"_componentId":"aa85aLD58JApo4DIvBOFqAe","handler":"onBtnClickToGet"}],"_N$transition":3,"transition":3,"_N$normalColor":{"__type__":"cc.Color","r":214,"g":214,"b":214}},{"__type__":"045a2SGe7RBVLBIutN8jPMM","node":{"__id__":6}}],"_prefab":{"__type__":"cc.PrefabInfo","root":{"__id__":1},"asset":{"__uuid__":"b5ayNS52NPdoOAV82HHCM9"},"fileId":"07jJ3k3OFF+ZUUvXiMRNFV"},"_contentSize":{"__type__":"cc.Size","width":350,"height":101},"_trs":{"__type__":"TypedArray","ctor":"Float64Array","array":[0,-357.384,0,0,0,0,1,1,1,1]}},{"__type__":"cc.Node","_name":"lblStar","_parent":{"__id__":6},"_components":[{"__id__":8},{"__type__":"cc.LabelOutline","node":{"__id__":7},"_color":{"__type__":"cc.Color"},"_width":5}],"_prefab":{"__type__":"cc.PrefabInfo","root":{"__id__":1},"asset":{"__uuid__":"b5ayNS52NPdoOAV82HHCM9"},"fileId":"4fafhReqZDe7KRg9n2jT5H"},"_contentSize":{"__type__":"cc.Size","width":164.25,"height":79.3},"_trs":{"__type__":"TypedArray","ctor":"Float64Array","array":[23.126,0,0,0,0,0,1,1,1,1]}},{"__type__":"cc.Label","node":{"__id__":7},"_materials":[{"__uuid__":"ecpdLyjvZBwrvm+cedCcQy"}],"_useOriginalSize":false,"_string":"钻石x6","_N$string":"钻石x6","_fontSize":45,"_lineHeight":55,"_N$file":{"__uuid__":"c17s8Hm4RNnY4RH3NxqkdJ"},"_isSystemFontUsed":false,"_N$horizontalAlign":1,"_N$verticalAlign":1},{"__type__":"cc.Node","_name":"btnWatchAd","_parent":{"__id__":3},"_children":[{"__id__":10}],"_components":[{"__type__":"cc.Sprite","node":{"__id__":9},"_materials":[{"__uuid__":"ecpdLyjvZBwrvm+cedCcQy"}],"_spriteFrame":{"__uuid__":"4eqdIXP2tCCpsyTLFn6PnA"}},{"__type__":"cc.Button","node":{"__id__":9},"clickEvents":[{"__type__":"cc.ClickEvent","target":{"__id__":1},"_componentId":"aa85aLD58JApo4DIvBOFqAe","handler":"onBtnClickToWatchAd"}],"_N$normalColor":{"__type__":"cc.Color","r":214,"g":214,"b":214}},{"__type__":"f0b2chRQo9BToIJVNXQnuuw","node":{"__id__":9}},{"__type__":"045a2SGe7RBVLBIutN8jPMM","node":{"__id__":9}}],"_prefab":{"__type__":"cc.PrefabInfo","root":{"__id__":1},"asset":{"__uuid__":"b5ayNS52NPdoOAV82HHCM9"},"fileId":"44EAuB5RFA77eb4U7STyqO"},"_contentSize":{"__type__":"cc.Size","width":350,"height":101},"_trs":{"__type__":"TypedArray","ctor":"Float64Array","array":[0,-239.051,0,0,0,0,1,1,1,1]}},{"__type__":"cc.Node","_name":"lblAd","_parent":{"__id__":9},"_components":[{"__type__":"cc.Label","node":{"__id__":10},"_materials":[{"__uuid__":"ecpdLyjvZBwrvm+cedCcQy"}],"_useOriginalSize":false,"_string":"免费领取","_N$string":"免费领取","_fontSize":45,"_lineHeight":55,"_N$file":{"__uuid__":"c17s8Hm4RNnY4RH3NxqkdJ"},"_isSystemFontUsed":false,"_N$horizontalAlign":1,"_N$verticalAlign":1},{"__type__":"cc.LabelOutline","node":{"__id__":10},"_color":{"__type__":"cc.Color"},"_width":5}],"_prefab":{"__type__":"cc.PrefabInfo","root":{"__id__":1},"asset":{"__uuid__":"b5ayNS52NPdoOAV82HHCM9"},"fileId":"36kIqZ9otI7LL8kOQJ8AXe"},"_contentSize":{"__type__":"cc.Size","width":190,"height":79.3},"_trs":{"__type__":"TypedArray","ctor":"Float64Array","array":[23.126,0,0,0,0,0,1,1,1,1]}},{"__type__":"cc.Node","_name":"New Label","_parent":{"__id__":3},"_components":[{"__type__":"cc.Label","node":{"__id__":11},"_materials":[{"__uuid__":"ecpdLyjvZBwrvm+cedCcQy"}],"_useOriginalSize":false,"_string":"金库","_N$string":"金库","_fontSize":60,"_lineHeight":65,"_N$file":{"__uuid__":"c17s8Hm4RNnY4RH3NxqkdJ"},"_isSystemFontUsed":false,"_N$horizontalAlign":1,"_N$verticalAlign":1},{"__type__":"cc.Widget","node":{"__id__":11},"_alignFlags":1},{"__type__":"ce702VEy5lPAImBY4a7Iyx3","node":{"__id__":11},"textId":171},{"__type__":"cc.LabelOutline","node":{"__id__":11},"_color":{"__type__":"cc.Color"},"_width":5}],"_prefab":{"__type__":"cc.PrefabInfo","root":{"__id__":1},"asset":{"__uuid__":"b5ayNS52NPdoOAV82HHCM9"},"fileId":"85dUSc1GRIGYj2uJVqfoG/"},"_contentSize":{"__type__":"cc.Size","width":130,"height":91.9},"_trs":{"__type__":"TypedArray","ctor":"Float64Array","array":[0,463.05,0,0,0,0,1,1,1,1]}},{"__type__":"cc.Node","_name":"lblMoney","_parent":{"__id__":3},"_components":[{"__id__":13},{"__type__":"cc.Widget","node":{"__id__":12},"_alignFlags":1,"_top":531.638},{"__type__":"cc.LabelOutline","node":{"__id__":12},"_color":{"__type__":"cc.Color"},"_width":5}],"_prefab":{"__type__":"cc.PrefabInfo","root":{"__id__":1},"asset":{"__uuid__":"b5ayNS52NPdoOAV82HHCM9"},"fileId":"ed9ZkaUjhCh4QPOcVubJtq"},"_color":{"__type__":"cc.Color","r":231,"g":231,"b":54},"_contentSize":{"__type__":"cc.Size","width":468.13,"height":117.1},"_trs":{"__type__":"TypedArray","ctor":"Float64Array","array":[0,-81.18800000000003,0,0,0,0,1,1,1,1]}},{"__type__":"cc.Label","node":{"__id__":12},"_materials":[{"__uuid__":"ecpdLyjvZBwrvm+cedCcQy"}],"_useOriginalSize":false,"_string":"$100,000","_N$string":"$100,000","_fontSize":80,"_lineHeight":85,"_N$file":{"__uuid__":"c17s8Hm4RNnY4RH3NxqkdJ"},"_isSystemFontUsed":false,"_N$horizontalAlign":1,"_N$verticalAlign":1},{"__type__":"cc.Node","_name":"lblMoneyTitle","_parent":{"__id__":3},"_components":[{"__type__":"cc.Label","node":{"__id__":14},"_materials":[{"__uuid__":"ecpdLyjvZBwrvm+cedCcQy"}],"_useOriginalSize":false,"_string":"看视频获取金币奖励","_N$string":"看视频获取金币奖励","_fontSize":60,"_lineHeight":65,"_N$file":{"__uuid__":"c17s8Hm4RNnY4RH3NxqkdJ"},"_isSystemFontUsed":false,"_N$horizontalAlign":1,"_N$verticalAlign":1},{"__type__":"cc.LabelOutline","node":{"__id__":14},"_color":{"__type__":"cc.Color"},"_width":5}],"_prefab":{"__type__":"cc.PrefabInfo","root":{"__id__":1},"asset":{"__uuid__":"b5ayNS52NPdoOAV82HHCM9"},"fileId":"28wNt2/nlAPa6Pj1LVKR22"},"_contentSize":{"__type__":"cc.Size","width":550,"height":91.9},"_trs":{"__type__":"TypedArray","ctor":"Float64Array","array":[0,302.299,0,0,0,0,1,1,1,1]}}],{"__type__":"cc.SpriteFrame","content":{"name":"btnStar","texture":"7fSCPFdEFGh5HKiBTzna5A","rect":[569,550,350,101],"offset":[0,0],"originalSize":[350,101],"capInsets":[154,0,154,0]}}]