[{"__type__":"cc.SpriteFrame","content":{"name":"popKuang_S","texture":"18gxpTh89LMbx6gPDjn0oX","rect":[0,0,730,1018],"offset":[0,0],"originalSize":[730,1018],"capInsets":[362,490,362,490]}},{"__type__":"cc.SpriteFrame","content":{"name":"btnAd","texture":"7fSCPFdEFGh5HKiBTzna5A","rect":[2,1056,350,101],"offset":[0,0],"originalSize":[350,101],"capInsets":[158,0,158,0]}},[{"__type__":"cc.Prefab","_name":"AutoMergeLayer","data":{"__id__":1}},{"__type__":"cc.Node","_name":"AutoMergeLayer","_children":[{"__id__":2},{"__id__":3}],"_components":[{"__type__":"cc.Widget","node":{"__id__":1},"_alignFlags":45},{"__type__":"9c3cbcBZchIdarxWRvDpY2E","node":{"__id__":1},"lblRTime":{"__id__":8},"lblStar":{"__id__":12}}],"_prefab":{"__type__":"cc.PrefabInfo","root":{"__id__":1},"asset":{"__uuid__":"8bMMBuIpxMJYO39LcjdQ63"},"fileId":"28ndCx9TVO+LoElKReSeKc"},"_contentSize":{"__type__":"cc.Size","width":1080,"height":1920},"_trs":{"__type__":"TypedArray","ctor":"Float64Array","array":[540,960,0,0,0,0,1,1,1,1]}},{"__type__":"cc.Node","_name":"bg","_parent":{"__id__":1},"_components":[{"__type__":"cc.Sprite","node":{"__id__":2},"_materials":[{"__uuid__":"ecpdLyjvZBwrvm+cedCcQy"}],"_spriteFrame":{"__uuid__":"a2MjXRFdtLlYQ5ouAFv/+R"},"_sizeMode":0},{"__type__":"cc.Widget","node":{"__id__":2},"_alignFlags":45,"_originalWidth":100,"_originalHeight":100}],"_prefab":{"__type__":"cc.PrefabInfo","root":{"__id__":1},"asset":{"__uuid__":"8bMMBuIpxMJYO39LcjdQ63"},"fileId":"c3NKF+ez5PTLZ3YXv3PkyY"},"_opacity":120,"_color":{"__type__":"cc.Color","r":46,"g":39,"b":39},"_contentSize":{"__type__":"cc.Size","width":1080,"height":1920},"_trs":{"__type__":"TypedArray","ctor":"Float64Array","array":[0,0,0,0,0,0,1,1,1,1]}},{"__type__":"cc.Node","_name":"popupFrame","_parent":{"__id__":1},"_children":[{"__id__":4},{"__id__":5},{"__id__":9},{"__id__":10},{"__id__":13}],"_components":[{"__type__":"cc.Sprite","node":{"__id__":3},"_materials":[{"__uuid__":"ecpdLyjvZBwrvm+cedCcQy"}],"_spriteFrame":{"__uuid__":"0eRtVld5lMv6UCPVe7Vj46"},"_type":1,"_sizeMode":0}],"_prefab":{"__type__":"cc.PrefabInfo","root":{"__id__":1},"asset":{"__uuid__":"8bMMBuIpxMJYO39LcjdQ63"},"fileId":"98Ao4Pac1CvYfbkj8cpgLB"},"_contentSize":{"__type__":"cc.Size","width":730,"height":1018},"_trs":{"__type__":"TypedArray","ctor":"Float64Array","array":[0,0,0,0,0,0,1,1,1,1]}},{"__type__":"cc.Node","_name":"New Label","_parent":{"__id__":3},"_components":[{"__type__":"cc.Label","node":{"__id__":4},"_materials":[{"__uuid__":"ecpdLyjvZBwrvm+cedCcQy"}],"_useOriginalSize":false,"_string":"自动合成","_N$string":"自动合成","_fontSize":60,"_lineHeight":65,"_N$file":{"__uuid__":"c17s8Hm4RNnY4RH3NxqkdJ"},"_isSystemFontUsed":false,"_N$horizontalAlign":1,"_N$verticalAlign":1},{"__type__":"cc.Widget","node":{"__id__":4},"_alignFlags":1},{"__type__":"ce702VEy5lPAImBY4a7Iyx3","node":{"__id__":4},"textId":183},{"__type__":"cc.LabelOutline","node":{"__id__":4},"_color":{"__type__":"cc.Color"},"_width":5}],"_prefab":{"__type__":"cc.PrefabInfo","root":{"__id__":1},"asset":{"__uuid__":"8bMMBuIpxMJYO39LcjdQ63"},"fileId":"d7WVfx6e1Cq6/+k0n0L62e"},"_contentSize":{"__type__":"cc.Size","width":250,"height":91.9},"_trs":{"__type__":"TypedArray","ctor":"Float64Array","array":[0,463.05,0,0,0,0,1,1,1,1]}},{"__type__":"cc.Node","_name":"lblRTime","_parent":{"__id__":3},"_children":[{"__id__":6},{"__id__":7}],"_components":[{"__id__":8},{"__type__":"ce702VEy5lPAImBY4a7Iyx3","node":{"__id__":5},"textId":184}],"_prefab":{"__type__":"cc.PrefabInfo","root":{"__id__":1},"asset":{"__uuid__":"8bMMBuIpxMJYO39LcjdQ63"},"fileId":"276kuVSiZBIb8pynSIrE9H"},"_contentSize":{"__type__":"cc.Size","width":570.98,"height":126},"_trs":{"__type__":"TypedArray","ctor":"Float64Array","array":[0,198.983,0,0,0,0,1,1,1,1]}},{"__type__":"cc.PrivateNode","_name":"RICHTEXT_CHILD","_objFlags":1024,"_parent":{"__id__":5},"_components":[{"__type__":"cc.Label","node":{"__id__":6},"_materials":[{"__uuid__":"ecpdLyjvZBwrvm+cedCcQy"}],"_string":"180s","_N$string":"180s","_fontSize":70,"_lineHeight":100,"_N$file":{"__uuid__":"c17s8Hm4RNnY4RH3NxqkdJ"},"_isSystemFontUsed":false,"_N$verticalAlign":1},{"__type__":"cc.LabelOutline","node":{"__id__":6},"_color":{"__type__":"cc.Color"},"_width":5}],"_prefab":{"__type__":"cc.PrefabInfo","root":{"__id__":1},"asset":{"__uuid__":"8bMMBuIpxMJYO39LcjdQ63"},"fileId":"49cYbNXGZJzolATBYkCum/"},"_color":{"__type__":"cc.Color","r":255,"g":209,"b":26},"_contentSize":{"__type__":"cc.Size","width":210.98,"height":136},"_anchorPoint":{"__type__":"cc.Vec2"},"_position":{"__type__":"cc.Vec3","x":-285.49,"y":-63},"_scale":{"__type__":"cc.Vec3","x":1,"y":1,"z":1},"_trs":{"__type__":"TypedArray","ctor":"Float64Array","array":[0,0,0,0,0,0,1,1,1,1]}},{"__type__":"cc.PrivateNode","_name":"RICHTEXT_CHILD","_objFlags":1024,"_parent":{"__id__":5},"_components":[{"__type__":"cc.Label","node":{"__id__":7},"_materials":[{"__uuid__":"ecpdLyjvZBwrvm+cedCcQy"}],"_string":"内自动合成","_N$string":"内自动合成","_fontSize":70,"_lineHeight":100,"_N$file":{"__uuid__":"c17s8Hm4RNnY4RH3NxqkdJ"},"_isSystemFontUsed":false,"_N$verticalAlign":1},{"__type__":"cc.LabelOutline","node":{"__id__":7},"_color":{"__type__":"cc.Color"},"_width":5}],"_prefab":{"__type__":"cc.PrefabInfo","root":{"__id__":1},"asset":{"__uuid__":"8bMMBuIpxMJYO39LcjdQ63"},"fileId":"38N6+MyAdPdri2lzVhx3kT"},"_contentSize":{"__type__":"cc.Size","width":360,"height":136},"_anchorPoint":{"__type__":"cc.Vec2"},"_position":{"__type__":"cc.Vec3","x":-74.51000000000002,"y":-63},"_scale":{"__type__":"cc.Vec3","x":1,"y":1,"z":1},"_trs":{"__type__":"TypedArray","ctor":"Float64Array","array":[0,0,0,0,0,0,1,1,1,1]}},{"__type__":"cc.RichText","node":{"__id__":5},"_isSystemFontUsed":false,"_N$string":"<outline color=black width=5><color=#ffd11a>180s</c><color=#ffffff>内自动合成</color></outline>","_N$horizontalAlign":1,"_N$fontSize":70,"_N$font":{"__uuid__":"c17s8Hm4RNnY4RH3NxqkdJ"},"_N$lineHeight":100},{"__type__":"cc.Node","_name":"btnClose","_parent":{"__id__":3},"_components":[{"__type__":"cc.Sprite","node":{"__id__":9},"_materials":[{"__uuid__":"ecpdLyjvZBwrvm+cedCcQy"}],"_spriteFrame":{"__uuid__":"aehRPGHDRHv4zgMuui1RMg"}},{"__type__":"cc.Widget","node":{"__id__":9},"_alignFlags":33},{"__type__":"cc.Button","node":{"__id__":9},"clickEvents":[{"__type__":"cc.ClickEvent","target":{"__id__":1},"_componentId":"9c3cbcBZchIdarxWRvDpY2E","handler":"onBtnClickToClose"}],"_N$transition":3,"transition":3,"_N$normalColor":{"__type__":"cc.Color","r":214,"g":214,"b":214}},{"__type__":"045a2SGe7RBVLBIutN8jPMM","node":{"__id__":9}},{"__type__":"03d50qD7WhNnpmfgnS9N+eO","node":{"__id__":9}}],"_prefab":{"__type__":"cc.PrefabInfo","root":{"__id__":1},"asset":{"__uuid__":"8bMMBuIpxMJYO39LcjdQ63"},"fileId":"2bOsqVmTtDMZ1JYZrSAmN/"},"_opacity":0,"_contentSize":{"__type__":"cc.Size","width":68,"height":68},"_trs":{"__type__":"TypedArray","ctor":"Float64Array","array":[331,475,0,0,0,0,1,1,1,1]}},{"__type__":"cc.Node","_name":"btnAutoMerge","_parent":{"__id__":3},"_children":[{"__id__":11}],"_components":[{"__type__":"cc.Sprite","node":{"__id__":10},"_materials":[{"__uuid__":"ecpdLyjvZBwrvm+cedCcQy"}],"_spriteFrame":{"__uuid__":"bddtvDcTlDVannbcUdYPRZ"}},{"__type__":"cc.Button","node":{"__id__":10},"clickEvents":[{"__type__":"cc.ClickEvent","target":{"__id__":1},"_componentId":"9c3cbcBZchIdarxWRvDpY2E","handler":"onBtnClickToAutoMerge"}],"_N$transition":3,"transition":3,"_N$normalColor":{"__type__":"cc.Color","r":214,"g":214,"b":214}},{"__type__":"cc.Widget","node":{"__id__":10},"_alignFlags":9,"_left":190,"_top":653.523},{"__type__":"045a2SGe7RBVLBIutN8jPMM","node":{"__id__":10}}],"_prefab":{"__type__":"cc.PrefabInfo","root":{"__id__":1},"asset":{"__uuid__":"8bMMBuIpxMJYO39LcjdQ63"},"fileId":"47DMMkyQJKQbnaXa9q0fCL"},"_contentSize":{"__type__":"cc.Size","width":350,"height":101},"_trs":{"__type__":"TypedArray","ctor":"Float64Array","array":[0,-195.02300000000002,0,0,0,0,1,1,1,1]}},{"__type__":"cc.Node","_name":"lblStar","_parent":{"__id__":10},"_components":[{"__id__":12},{"__type__":"cc.LabelOutline","node":{"__id__":11},"_color":{"__type__":"cc.Color"},"_width":5}],"_prefab":{"__type__":"cc.PrefabInfo","root":{"__id__":1},"asset":{"__uuid__":"8bMMBuIpxMJYO39LcjdQ63"},"fileId":"b6z1vASWRMjrUCwhnAsJDx"},"_contentSize":{"__type__":"cc.Size","width":80.05,"height":79.3},"_trs":{"__type__":"TypedArray","ctor":"Float64Array","array":[13.563,0,0,0,0,0,1,1,1,1]}},{"__type__":"cc.Label","node":{"__id__":11},"_materials":[{"__uuid__":"ecpdLyjvZBwrvm+cedCcQy"}],"_useOriginalSize":false,"_string":"15","_N$string":"15","_fontSize":45,"_lineHeight":55,"_N$file":{"__uuid__":"c17s8Hm4RNnY4RH3NxqkdJ"},"_isSystemFontUsed":false,"_N$horizontalAlign":1,"_N$verticalAlign":1},{"__type__":"cc.Node","_name":"btnWatchAd","_parent":{"__id__":3},"_children":[{"__id__":14}],"_components":[{"__type__":"cc.Sprite","node":{"__id__":13},"_materials":[{"__uuid__":"ecpdLyjvZBwrvm+cedCcQy"}],"_spriteFrame":{"__uuid__":"4eqdIXP2tCCpsyTLFn6PnA"}},{"__type__":"cc.Button","node":{"__id__":13},"clickEvents":[{"__type__":"cc.ClickEvent","target":{"__id__":1},"_componentId":"9c3cbcBZchIdarxWRvDpY2E","handler":"onBtnClickToWatchAd"}],"_N$transition":3,"transition":3,"_N$normalColor":{"__type__":"cc.Color","r":214,"g":214,"b":214}},{"__type__":"cc.Widget","node":{"__id__":13},"_alignFlags":33,"_right":190,"_top":487.389},{"__type__":"045a2SGe7RBVLBIutN8jPMM","node":{"__id__":13}},{"__type__":"f0b2chRQo9BToIJVNXQnuuw","node":{"__id__":13}}],"_prefab":{"__type__":"cc.PrefabInfo","root":{"__id__":1},"asset":{"__uuid__":"8bMMBuIpxMJYO39LcjdQ63"},"fileId":"670ddpI5NP1pp+pM4z6whI"},"_contentSize":{"__type__":"cc.Size","width":350,"height":101},"_trs":{"__type__":"TypedArray","ctor":"Float64Array","array":[0,-28.88900000000001,0,0,0,0,1,1,1,1]}},{"__type__":"cc.Node","_name":"New Label","_parent":{"__id__":13},"_components":[{"__type__":"cc.Label","node":{"__id__":14},"_materials":[{"__uuid__":"ecpdLyjvZBwrvm+cedCcQy"}],"_useOriginalSize":false,"_string":"免费领取","_N$string":"免费领取","_fontSize":45,"_lineHeight":55,"_N$file":{"__uuid__":"c17s8Hm4RNnY4RH3NxqkdJ"},"_isSystemFontUsed":false,"_N$horizontalAlign":1,"_N$verticalAlign":1},{"__type__":"ce702VEy5lPAImBY4a7Iyx3","node":{"__id__":14},"_enabled":false,"textId":199},{"__type__":"cc.LabelOutline","node":{"__id__":14},"_color":{"__type__":"cc.Color"},"_width":5}],"_prefab":{"__type__":"cc.PrefabInfo","root":{"__id__":1},"asset":{"__uuid__":"8bMMBuIpxMJYO39LcjdQ63"},"fileId":"d0Mz1twClGLaYephHQmzss"},"_contentSize":{"__type__":"cc.Size","width":190,"height":79.3},"_trs":{"__type__":"TypedArray","ctor":"Float64Array","array":[17,0,0,0,0,0,1,1,1,1]}}],{"__type__":"cc.SpriteFrame","content":{"name":"default_sprite_splash","texture":"02delMVqdBD70a/HSD99FK","rect":[0,0,2,2],"offset":[0,0],"originalSize":[2,2],"capInsets":[0,0,0,0]}},{"__type__":"cc.SpriteFrame","content":{"name":"btnClose","texture":"7fSCPFdEFGh5HKiBTzna5A","rect":[78,1785,68,68],"offset":[0,0],"originalSize":[68,68],"capInsets":[0,0,0,0]}},{"__type__":"cc.SpriteFrame","content":{"name":"btnStar","texture":"7fSCPFdEFGh5HKiBTzna5A","rect":[569,550,350,101],"offset":[0,0],"originalSize":[350,101],"capInsets":[154,0,154,0]}}]